mplog/__init__.py
mplog/client.py
mplog/config.py
mplog/server/__init__.py
mplog/server/_sql_scripts.py
mplog/server/app.py
mplog/server/dbm.py
mplog/server/static/jquery-3.3.1.min.js
mplog/server/static/main.css
mplog/server/static/main.js
mplog/server/static/panel.html
mplog-0.2.1a1.dist-info/DESCRIPTION.rst
mplog-0.2.1a1.dist-info/METADATA
mplog-0.2.1a1.dist-info/RECORD
mplog-0.2.1a1.dist-info/WHEEL
mplog-0.2.1a1.dist-info/entry_points.txt
mplog-0.2.1a1.dist-info/metadata.json
mplog-0.2.1a1.dist-info/top_level.txt
