Metadata-Version: 2.0
Name: mplog
Version: 0.2.1a1
Summary: a python library for multi-processing logging
Home-page: https://github.com/chkap/mplog
Author: chkap
Author-email: chkhappy@hotmail.com
License: MIT
Project-URL: Documentation, https://github.com/chkap/mplog
Project-URL: Source, https://github.com/chkap/mplog
Project-URL: Tracker, https://github.com/chkap/mplog/issues
Requires-Dist: flask
Requires-Dist: gevent
